patch_conv/__init__.py
patch_conv/__version__.py
patch_conv/module.py
patch_conv/utils.py
patch_conv-0.0.1b0.dist-info/LICENSE.txt
patch_conv-0.0.1b0.dist-info/METADATA
patch_conv-0.0.1b0.dist-info/WHEEL
patch_conv-0.0.1b0.dist-info/top_level.txt
patch_conv-0.0.1b0.dist-info/RECORD
