Metadata-Version: 2.1
Name: patch_conv
Version: 0.0.1b0
Summary: Patch convolution to avoid large GPU memory usage of Conv2D
Home-page: https://github.com/mit-han-lab/patch_conv
Author: Muyang Li, Ligeng Zhu, and Tianle Cai
Author-email: muyangli@mit.edu
Classifier: Programming Language :: Python :: 3
Classifier: Operating System :: OS Independent
Requires-Python: >=3.10
License-File: LICENSE.txt
Requires-Dist: torch
